core_types/__init__.py
core_types/core_classes/__init__.py
core_types/core_classes/base_controller.py
core_types/core_classes/base_database.py
core_types/core_classes/base_factory.py
core_types/core_classes/base_request.py
core_types/core_classes/base_response.py
core_types/core_interfaces/__init__.py
core_types/core_interfaces/i_association.py
core_types/core_interfaces/i_field_group_detail_status.py
core_types/core_types/__init__.py
core_types/core_types/analysis_type.py
core_types/core_types/analysis_type_detail.py
core_types/core_types/field_group.py
core_types/core_types/field_group_detail.py
core_types/core_types/read_request_object.py
core_types/core_types/response_object.py
core_types/core_types/save_request_item_object.py
core_types/core_types/save_request_object.py
core_types/core_types/title.py
lib_core_test-1.0.0.dist-info/METADATA
lib_core_test-1.0.0.dist-info/WHEEL
lib_core_test-1.0.0.dist-info/top_level.txt
lib_core_test-1.0.0.dist-info/RECORD
